wrapit/__init__.py
wrapit/api.py
wrapit/loader.py
wrapit/parser.py
wrapit-0.2.2.dist-info/DESCRIPTION.rst
wrapit-0.2.2.dist-info/METADATA
wrapit-0.2.2.dist-info/RECORD
wrapit-0.2.2.dist-info/WHEEL
wrapit-0.2.2.dist-info/metadata.json
wrapit-0.2.2.dist-info/top_level.txt
