Metadata-Version: 2.0
Name: wrapit
Version: 0.2.2
Summary: A task loader for doit that supports argparse console scripts
Home-page: https://github.com/rbeagrie/wrapit
Author: Rob Beagrie
Author-email: rob@beagrie.com
License: MIT
Keywords: doit development console_scripts build_tools
Platform: UNKNOWN
Classifier: Development Status :: 3 - Alpha
Classifier: Intended Audience :: Developers
Classifier: Topic :: Software Development :: Build Tools
Classifier: License :: OSI Approved :: MIT License
Classifier: Programming Language :: Python :: 2
Classifier: Programming Language :: Python :: 2.6
Classifier: Programming Language :: Python :: 2.7
Requires-Dist: doit (==0.29.0); python_version<"3.0"
Requires-Dist: doit (==0.30.0); python_version>="3.0"
